odoo/addons/ssi_accountant_report_operating_unit/README.rst
odoo/addons/ssi_accountant_report_operating_unit/__init__.py
odoo/addons/ssi_accountant_report_operating_unit/__manifest__.py
odoo/addons/ssi_accountant_report_operating_unit/models/__init__.py
odoo/addons/ssi_accountant_report_operating_unit/models/accountant_assurance_report.py
odoo/addons/ssi_accountant_report_operating_unit/models/accountant_nonassurance_report.py
odoo/addons/ssi_accountant_report_operating_unit/security/ir_rule/assurance_report.xml
odoo/addons/ssi_accountant_report_operating_unit/security/ir_rule/nonassurance_report.xml
odoo/addons/ssi_accountant_report_operating_unit/security/res_group/assurance_report.xml
odoo/addons/ssi_accountant_report_operating_unit/security/res_group/nonassurance_report.xml
odoo/addons/ssi_accountant_report_operating_unit/static/description/icon.png
odoo/addons/ssi_accountant_report_operating_unit/views/assurance_report_views.xml
odoo/addons/ssi_accountant_report_operating_unit/views/nonassurance_report_views.xml
odoo14_addon_ssi_accountant_report_operating_unit-14.0.1.1.0.dist-info/METADATA
odoo14_addon_ssi_accountant_report_operating_unit-14.0.1.1.0.dist-info/WHEEL
odoo14_addon_ssi_accountant_report_operating_unit-14.0.1.1.0.dist-info/top_level.txt
odoo14_addon_ssi_accountant_report_operating_unit-14.0.1.1.0.dist-info/RECORD
